seaportpy/__init__.py
seaportpy/abi/ERC1155.py
seaportpy/abi/ERC20.py
seaportpy/abi/ERC721.py
seaportpy/abi/Seaport.py
seaportpy/abi/__init__.py
seaportpy/constants.py
seaportpy/seaport.py
seaportpy/types.py
seaportpy/utils/__init__.py
seaportpy/utils/balance.py
seaportpy/utils/balance_and_approval_check.py
seaportpy/utils/fulfill.py
seaportpy/utils/gcd.py
seaportpy/utils/hex_utils.py
seaportpy/utils/item.py
seaportpy/utils/merkletree.py
seaportpy/utils/order.py
seaportpy/utils/pydantic.py
seaportpy/utils/usecase.py
seaportpy-1.0.0.dist-info/LICENSE
seaportpy-1.0.0.dist-info/WHEEL
seaportpy-1.0.0.dist-info/METADATA
seaportpy-1.0.0.dist-info/RECORD
